{
    "word_index": {
        "<OOV>": 1,
        "the": 2,
        "to": 3,
        "is": 4,
        "a": 5,
        "was": 6,
        "and": 7,
        "in": 8,
        "of": 9,
        "i": 10,
        "she": 11,
        "he": 12,
        "for": 13,
        "on": 14,
        "at": 15,
        "are": 16,
        "by": 17,
        "it": 18,
        "this": 19,
        "new": 20,
        "but": 21,
        "you": 22,
        "than": 23,
        "have": 24,
        "her": 25,
        "has": 26,
        "with": 27,
        "they": 28,
        "were": 29,
        "his": 30,
        "be": 31,
        "my": 32,
        "more": 33,
        "will": 34,
        "if": 35,
        "their": 36,
        "it's": 37,
        "store": 38,
        "book": 39,
        "that": 40,
        "work": 41,
        "not": 42,
        "car": 43,
        "students": 44,
        "we": 45,
        "very": 46,
        "its": 47,
        "movie": 48,
        "an": 49,
        "cake": 50,
        "went": 51,
        "no": 52,
        "project": 53,
        "team": 54,
        "about": 55,
        "need": 56,
        "he's": 57,
        "been": 58,
        "last": 59,
        "meeting": 60,
        "park": 61,
        "can": 62,
        "dog": 63,
        "had": 64,
        "needs": 65,
        "going": 66,
        "concert": 67,
        "can't": 68,
        "party": 69,
        "me": 70,
        "beautiful": 71,
        "so": 72,
        "one": 73,
        "day": 74,
        "didn't": 75,
        "delicious": 76,
        "your": 77,
        "time": 78,
        "company": 79,
        "they're": 80,
        "every": 81,
        "would": 82,
        "great": 83,
        "play": 84,
        "some": 85,
        "most": 86,
        "flowers": 87,
        "teacher": 88,
        "as": 89,
        "many": 90,
        "any": 91,
        "she's": 92,
        "don't": 93,
        "all": 94,
        "when": 95,
        "go": 96,
        "playing": 97,
        "know": 98,
        "could": 99,
        "computer": 100,
        "room": 101,
        "from": 102,
        "house": 103,
        "him": 104,
        "phone": 105,
        "yesterday": 106,
        "people": 107,
        "children": 108,
        "doctor": 109,
        "reading": 110,
        "working": 111,
        "weather": 112,
        "i'm": 113,
        "city": 114,
        "bought": 115,
        "night": 116,
        "cat": 117,
        "food": 118,
        "table": 119,
        "books": 120,
        "up": 121,
        "like": 122,
        "manager": 123,
        "beach": 124,
        "out": 125,
        "group": 126,
        "how": 127,
        "pm": 128,
        "do": 129,
        "event": 130,
        "restaurant": 131,
        "well": 132,
        "less": 133,
        "am": 134,
        "soccer": 135,
        "garden": 136,
        "before": 137,
        "package": 138,
        "late": 139,
        "interesting": 140,
        "too": 141,
        "together": 142,
        "after": 143,
        "conference": 144,
        "them": 145,
        "doesn't": 146,
        "there": 147,
        "want": 148,
        "software": 149,
        "train": 150,
        "eat": 151,
        "dinner": 152,
        "music": 153,
        "few": 154,
        "or": 155,
        "plants": 156,
        "buy": 157,
        "hard": 158,
        "job": 159,
        "old": 160,
        "take": 161,
        "tree": 162,
        "due": 163,
        "building": 164,
        "outside": 165,
        "long": 166,
        "asked": 167,
        "artist": 168,
        "during": 169,
        "performance": 170,
        "make": 171,
        "vacation": 172,
        "study": 173,
        "two": 174,
        "recipe": 175,
        "decided": 176,
        "waiting": 177,
        "which": 178,
        "made": 179,
        "homework": 180,
        "finish": 181,
        "today": 182,
        "week": 183,
        "museum": 184,
        "works": 185,
        "help": 186,
        "please": 187,
        "water": 188,
        "improve": 189,
        "pizza": 190,
        "school": 191,
        "over": 192,
        "birds": 193,
        "library": 194,
        "company's": 195,
        "learn": 196,
        "movies": 197,
        "good": 198,
        "tired": 199,
        "got": 200,
        "person": 201,
        "i've": 202,
        "report": 203,
        "morning": 204,
        "exam": 205,
        "family": 206,
        "our": 207,
        "delivered": 208,
        "game": 209,
        "always": 210,
        "who": 211,
        "better": 212,
        "friendly": 213,
        "next": 214,
        "cook": 215,
        "rain": 216,
        "employees": 217,
        "dishes": 218,
        "unique": 219,
        "favorite": 220,
        "famous": 221,
        "found": 222,
        "wants": 223,
        "should": 224,
        "talented": 225,
        "tomorrow": 226,
        "studying": 227,
        "year": 228,
        "product": 229,
        "taking": 230,
        "set": 231,
        "change": 232,
        "trees": 233,
        "lot": 234,
        "because": 235,
        "bus": 236,
        "problem": 237,
        "skills": 238,
        "tonight": 239,
        "think": 240,
        "walk": 241,
        "chef": 242,
        "test": 243,
        "author": 244,
        "ingredients": 245,
        "class": 246,
        "trip": 247,
        "groceries": 248,
        "gym": 249,
        "presentation": 250,
        "using": 251,
        "guitar": 252,
        "took": 253,
        "coffee": 254,
        "couldn't": 255,
        "seen": 256,
        "must": 257,
        "find": 258,
        "other": 259,
        "where": 260,
        "athlete": 261,
        "shoes": 262,
        "hotel": 263,
        "amazing": 264,
        "training": 265,
        "research": 266,
        "tried": 267,
        "battery": 268,
        "crowded": 269,
        "expensive": 270,
        "includes": 271,
        "guests": 272,
        "slow": 273,
        "tourists": 274,
        "collection": 275,
        "paintings": 276,
        "enjoyed": 277,
        "painting": 278,
        "5": 279,
        "3": 280,
        "tail": 281,
        "i'll": 282,
        "down": 283,
        "wanted": 284,
        "use": 285,
        "sun": 286,
        "said": 287,
        "running": 288,
        "pair": 289,
        "variety": 290,
        "friends": 291,
        "enjoy": 292,
        "while": 293,
        "development": 294,
        "john": 295,
        "eggs": 296,
        "feeling": 297,
        "lost": 298,
        "offers": 299,
        "life": 300,
        "watch": 301,
        "worth": 302,
        "told": 303,
        "user": 304,
        "requires": 305,
        "scientist": 306,
        "dress": 307,
        "gardener": 308,
        "field": 309,
        "fun": 310,
        "plane": 311,
        "mechanic": 312,
        "9": 313,
        "patient": 314,
        "pictures": 315,
        "everyone": 316,
        "difficult": 317,
        "ice": 318,
        "off": 319,
        "parked": 320,
        "home": 321,
        "weekend": 322,
        "making": 323,
        "met": 324,
        "come": 325,
        "30": 326,
        "street": 327,
        "10": 328,
        "early": 329,
        "cold": 330,
        "money": 331,
        "world": 332,
        "summer": 333,
        "month": 334,
        "read": 335,
        "noise": 336,
        "flying": 337,
        "clothes": 338,
        "keys": 339,
        "features": 340,
        "friend": 341,
        "cooking": 342,
        "written": 343,
        "likes": 344,
        "owner": 345,
        "boy": 346,
        "soon": 347,
        "baked": 348,
        "known": 349,
        "exercise": 350,
        "what": 351,
        "won": 352,
        "best": 353,
        "get": 354,
        "data": 355,
        "spring": 356,
        "answer": 357,
        "baby": 358,
        "hungry": 359,
        "player": 360,
        "8": 361,
        "musician": 362,
        "competition": 363,
        "complete": 364,
        "deadline": 365,
        "results": 366,
        "policies": 367,
        "loudly": 368,
        "history": 369,
        "informative": 370,
        "plans": 371,
        "learning": 372,
        "started": 373,
        "products": 374,
        "climate": 375,
        "cream": 376,
        "apple": 377,
        "decorated": 378,
        "bird": 379,
        "mountain": 380,
        "solve": 381,
        "road": 382,
        "window": 383,
        "held": 384,
        "office": 385,
        "7": 386,
        "won't": 387,
        "here": 388,
        "believe": 389,
        "ate": 390,
        "sells": 391,
        "calls": 392,
        "gave": 393,
        "20": 394,
        "into": 395,
        "there's": 396,
        "doing": 397,
        "travel": 398,
        "you're": 399,
        "way": 400,
        "article": 401,
        "ever": 402,
        "south": 403,
        "washed": 404,
        "growing": 405,
        "enjoys": 406,
        "show": 407,
        "looking": 408,
        "science": 409,
        "having": 410,
        "issues": 411,
        "top": 412,
        "2": 413,
        "meet": 414,
        "walking": 415,
        "broken": 416,
        "longer": 417,
        "various": 418,
        "man": 419,
        "brother": 420,
        "thought": 421,
        "eating": 422,
        "program": 423,
        "fixed": 424,
        "see": 425,
        "writing": 426,
        "design": 427,
        "create": 428,
        "machine": 429,
        "temperature": 430,
        "service": 431,
        "hours": 432,
        "basketball": 433,
        "dogs": 434,
        "kids": 435,
        "plays": 436,
        "speech": 437,
        "race": 438,
        "goal": 439,
        "bake": 440,
        "sale": 441,
        "engine": 442,
        "strange": 443,
        "speak": 444,
        "chocolate": 445,
        "employee": 446,
        "bad": 447,
        "wrong": 448,
        "audience": 449,
        "course": 450,
        "series": 451,
        "couple": 452,
        "desk": 453,
        "number": 454,
        "challenging": 455,
        "played": 456,
        "impressive": 457,
        "tell": 458,
        "attending": 459,
        "heavy": 460,
        "expert": 461,
        "ball": 462,
        "sitting": 463,
        "meal": 464,
        "wearing": 465,
        "wall": 466,
        "minutes": 467,
        "wallet": 468,
        "issue": 469,
        "end": 470,
        "faster": 471,
        "vegetables": 472,
        "put": 473,
        "delayed": 474,
        "wide": 475,
        "provides": 476,
        "saw": 477,
        "quite": 478,
        "laptop": 479,
        "never": 480,
        "bring": 481,
        "anything": 482,
        "visited": 483,
        "countries": 484,
        "studied": 485,
        "strong": 486,
        "members": 487,
        "future": 488,
        "quality": 489,
        "exhibition": 490,
        "efficient": 491,
        "powerful": 492,
        "does": 493,
        "aimed": 494,
        "now": 495,
        "goes": 496,
        "blooming": 497,
        "write": 498,
        "leave": 499,
        "perform": 500,
        "paint": 501,
        "photographer": 502,
        "bed": 503,
        "start": 504,
        "address": 505,
        "excited": 506,
        "filled": 507,
        "story": 508,
        "effects": 509,
        "grow": 510,
        "university": 511,
        "forward": 512,
        "earth": 513,
        "did": 514,
        "art": 515,
        "modern": 516,
        "hand": 517,
        "planning": 518,
        "energy": 519,
        "through": 520,
        "government": 521,
        "social": 522,
        "arrive": 523,
        "back": 524,
        "arrived": 525,
        "starts": 526,
        "small": 527,
        "quiet": 528,
        "quick": 529,
        "high": 530,
        "sugar": 531,
        "same": 532,
        "then": 533,
        "shelf": 534,
        "clothing": 535,
        "listen": 536,
        "sing": 537,
        "girl": 538,
        "love": 539,
        "00": 540,
        "free": 541,
        "milk": 542,
        "colors": 543,
        "boring": 544,
        "teaches": 545,
        "both": 546,
        "that's": 547,
        "ceo": 548,
        "furniture": 549,
        "organized": 550,
        "discuss": 551,
        "submit": 552,
        "tall": 553,
        "also": 554,
        "opinion": 555,
        "communication": 556,
        "leadership": 557,
        "three": 558,
        "careful": 559,
        "lunch": 560,
        "repaired": 561,
        "mail": 562,
        "games": 563,
        "paris": 564,
        "evening": 565,
        "6": 566,
        "lab": 567,
        "watered": 568,
        "papers": 569,
        "picture": 570,
        "model": 571,
        "hour": 572,
        "storm": 573,
        "cookies": 574,
        "volunteers": 575,
        "helping": 576,
        "winter": 577,
        "oven": 578,
        "icing": 579,
        "quickly": 580,
        "list": 581,
        "hands": 582,
        "musicians": 583,
        "flights": 584,
        "kitchen": 585,
        "instruments": 586,
        "crowd": 587,
        "community": 588,
        "wedding": 589,
        "gallery": 590,
        "scientists": 591,
        "perfect": 592,
        "articles": 593,
        "novel": 594,
        "club": 595,
        "pass": 596,
        "around": 597,
        "used": 598,
        "stop": 599,
        "technology": 600,
        "band": 601,
        "preparing": 602,
        "above": 603,
        "workers": 604,
        "piano": 605,
        "cleaning": 606,
        "ancient": 607,
        "passengers": 608,
        "screen": 609,
        "view": 610,
        "color": 611,
        "beauty": 612,
        "lives": 613,
        "since": 614,
        "river": 615,
        "located": 616,
        "shop": 617,
        "based": 618,
        "news": 619,
        "door": 620,
        "chased": 621,
        "box": 622,
        "fix": 623,
        "trained": 624,
        "email": 625,
        "enough": 626,
        "1": 627,
        "student": 628,
        "16": 629,
        "raining": 630,
        "green": 631,
        "letter": 632,
        "town": 633,
        "sister": 634,
        "shining": 635,
        "loves": 636,
        "interview": 637,
        "routine": 638,
        "mistake": 639,
        "us": 640,
        "however": 641,
        "experiment": 642,
        "math": 643,
        "policy": 644,
        "luxurious": 645,
        "needed": 646,
        "busy": 647,
        "parents": 648,
        "shirt": 649,
        "apples": 650,
        "cover": 651,
        "place": 652,
        "flies": 653,
        "such": 654,
        "medicine": 655,
        "sarah": 656,
        "magazine": 657,
        "latest": 658,
        "give": 659,
        "finished": 660,
        "presented": 661,
        "customer": 662,
        "much": 663,
        "focused": 664,
        "errors": 665,
        "important": 666,
        "expected": 667,
        "hair": 668,
        "decision": 669,
        "swimming": 670,
        "covers": 671,
        "live": 672,
        "analysis": 673,
        "problems": 674,
        "dropped": 675,
        "gonna": 676,
        "aims": 677,
        "tv": 678,
        "topics": 679,
        "just": 680,
        "advised": 681,
        "completed": 682,
        "sleep": 683,
        "birthday": 684,
        "plant": 685,
        "open": 686,
        "experienced": 687,
        "sure": 688,
        "increased": 689,
        "salt": 690,
        "under": 691,
        "personal": 692,
        "between": 693,
        "walked": 694,
        "true": 695,
        "drive": 696,
        "ran": 697,
        "especially": 698,
        "mind": 699,
        "heard": 700,
        "things": 701,
        "35": 702,
        "planted": 703,
        "kind": 704,
        "rome": 705,
        "taste": 706,
        "offer": 707,
        "board": 708,
        "abilities": 709,
        "wait": 710,
        "dessert": 711,
        "barking": 712,
        "snow": 713,
        "twice": 714,
        "fire": 715,
        "louder": 716,
        "words": 717,
        "prepared": 718,
        "harder": 719,
        "released": 720,
        "engaging": 721,
        "served": 722,
        "criticized": 723,
        "discussing": 724,
        "business": 725,
        "resources": 726,
        "plan": 727,
        "programming": 728,
        "result": 729,
        "happened": 730,
        "artist's": 731,
        "nothing": 732,
        "system": 733,
        "either": 734,
        "beautifully": 735,
        "assignments": 736,
        "six": 737,
        "carrier": 738,
        "airplane": 739,
        "listening": 740,
        "teach": 741,
        "classroom": 742,
        "pool": 743,
        "dance": 744,
        "build": 745,
        "launch": 746,
        "weeks": 747,
        "visit": 748,
        "exams": 749,
        "waiter": 750,
        "driver": 751,
        "break": 752,
        "organize": 753,
        "shopping": 754,
        "close": 755,
        "charge": 756,
        "inconclusive": 757,
        "committed": 758,
        "computers": 759,
        "makes": 760,
        "coins": 761,
        "displayed": 762,
        "saturday": 763,
        "cleaned": 764,
        "orchestra": 765,
        "events": 766,
        "tasks": 767,
        "staff": 768,
        "sound": 769,
        "range": 770,
        "mountains": 771,
        "across": 772,
        "fish": 773,
        "different": 774,
        "offered": 775,
        "stars": 776,
        "hikers": 777,
        "theater": 778,
        "economy": 779,
        "months": 780,
        "instructions": 781,
        "follow": 782,
        "topic": 783,
        "vase": 784,
        "questions": 785,
        "human": 786,
        "turn": 787,
        "tea": 788,
        "europe": 789,
        "giving": 790,
        "species": 791,
        "visiting": 792,
        "celebrating": 793,
        "victory": 794,
        "architecture": 795,
        "message": 796,
        "speaker": 797,
        "fresh": 798,
        "damaged": 799,
        "friday": 800,
        "interested": 801,
        "prefer": 802,
        "instead": 803,
        "along": 804,
        "traveling": 805,
        "jumped": 806,
        "talking": 807,
        "shared": 808,
        "bag": 809,
        "song": 810,
        "haven't": 811,
        "sent": 812,
        "whole": 813,
        "dead": 814,
        "dentist": 815,
        "each": 816,
        "4": 817,
        "celebrity": 818,
        "bank": 819,
        "11": 820,
        "launching": 821,
        "12": 822,
        "13": 823,
        "14": 824,
        "15": 825,
        "17": 826,
        "18": 827,
        "boys": 828,
        "19": 829,
        "blue": 830,
        "21": 831,
        "22": 832,
        "23": 833,
        "24": 834,
        "25": 835,
        "question": 836,
        "26": 837,
        "27": 838,
        "28": 839,
        "29": 840,
        "31": 841,
        "32": 842,
        "33": 843,
        "fast": 844,
        "34": 845,
        "36": 846,
        "37": 847,
        "38": 848,
        "39": 849,
        "40": 850,
        "41": 851,
        "42": 852,
        "43": 853,
        "44": 854,
        "full": 855,
        "46": 856,
        "47": 857,
        "siblings": 858,
        "48": 859,
        "49": 860,
        "bright": 861,
        "50": 862,
        "electronics": 863,
        "candidate": 864,
        "failed": 865,
        "flat": 866,
        "regularly": 867,
        "sorry": 868,
        "smart": 869,
        "nice": 870,
        "phone's": 871,
        "sweet": 872,
        "clean": 873,
        "dancer": 874,
        "leaving": 875,
        "snacks": 876,
        "weight": 877,
        "pollution": 878,
        "health": 879,
        "court": 880,
        "ends": 881,
        "upgrade": 882,
        "mother": 883,
        "happy": 884,
        "large": 885,
        "felt": 886,
        "loud": 887,
        "dancing": 888,
        "ready": 889,
        "lecture": 890,
        "projects": 891,
        "save": 892,
        "puppy": 893,
        "let's": 894,
        "oranges": 895,
        "judge": 896,
        "basket": 897,
        "drink": 898,
        "eye": 899,
        "watched": 900,
        "look": 901,
        "gift": 902,
        "managed": 903,
        "colleagues": 904,
        "conducted": 905,
        "growth": 906,
        "warmer": 907,
        "budget": 908,
        "worked": 909,
        "workshop": 910,
        "returned": 911,
        "dish": 912,
        "discussed": 913,
        "fuel": 914,
        "spicy": 915,
        "actor": 916,
        "containing": 917,
        "journalist": 918,
        "recent": 919,
        "yours": 920,
        "previous": 921,
        "worse": 922,
        "easier": 923,
        "activities": 924,
        "prices": 925,
        "succeed": 926,
        "network": 927,
        "skilled": 928,
        "exciting": 929,
        "exercises": 930,
        "photography": 931,
        "innovation": 932,
        "experience": 933,
        "strategy": 934,
        "involves": 935,
        "focuses": 936,
        "strict": 937,
        "become": 938,
        "earlier": 939,
        "successful": 940,
        "carefully": 941,
        "completely": 942,
        "idea": 943,
        "attention": 944,
        "infrastructure": 945,
        "ideas": 946,
        "innovative": 947,
        "gone": 948,
        "ask": 949,
        "might": 950,
        "law": 951,
        "send": 952,
        "lately": 953,
        "isn't": 954,
        "progress": 955,
        "scene": 956,
        "real": 957,
        "trying": 958,
        "efficiently": 959,
        "instructed": 960,
        "market": 961,
        "lack": 962,
        "success": 963,
        "excellent": 964,
        "properly": 965,
        "times": 966,
        "fly": 967,
        "wash": 968,
        "takes": 969,
        "gold": 970,
        "neighbors": 971,
        "falling": 972,
        "york": 973,
        "department": 974,
        "complicated": 975,
        "swim": 976,
        "wilting": 977,
        "professor": 978,
        "away": 979,
        "hiding": 980,
        "chasing": 981,
        "ticket": 982,
        "healthy": 983,
        "watching": 984,
        "scheduled": 985,
        "beside": 986,
        "kept": 987,
        "lying": 988,
        "came": 989,
        "belong": 990,
        "exercising": 991,
        "hire": 992,
        "include": 993,
        "years": 994,
        "knew": 995,
        "final": 996,
        "car's": 997,
        "schedule": 998,
        "little": 999,
        "climb": 1000,
        "wasn't": 1001,
        "umbrella": 1002,
        "barked": 1003,
        "bread": 1004,
        "john's": 1005,
        "right": 1006,
        "caused": 1007,
        "regulations": 1008,
        "reads": 1009,
        "traveled": 1010,
        "closed": 1011,
        "quietly": 1012,
        "hear": 1013,
        "without": 1014,
        "chew": 1015,
        "rock": 1016,
        "catches": 1017,
        "worm": 1018,
        "actions": 1019,
        "horse": 1020,
        "keep": 1021,
        "wheel": 1022,
        "only": 1023,
        "eaten": 1024,
        "performed": 1025,
        "cooked": 1026,
        "encourage": 1027,
        "broke": 1028,
        "received": 1029,
        "public": 1030,
        "still": 1031,
        "cut": 1032,
        "worn": 1033,
        "run": 1034,
        "hotter": 1035,
        "feature": 1036,
        "funny": 1037,
        "athlete's": 1038,
        "creatively": 1039,
        "education": 1040,
        "goals": 1041,
        "summary": 1042,
        "canceled": 1043,
        "teamwork": 1044,
        "ya": 1045,
        "caught": 1046,
        "ain't": 1047,
        "services": 1048,
        "team's": 1049,
        "secret": 1050,
        "breakfast": 1051,
        "marketing": 1052,
        "improvement": 1053,
        "professional": 1054,
        "skill": 1055,
        "united": 1056,
        "experiments": 1057,
        "perfectly": 1058,
        "performs": 1059,
        "video": 1060,
        "catch": 1061,
        "mouse": 1062,
        "friend's": 1063,
        "squirrel": 1064,
        "sunset": 1065,
        "match": 1066,
        "forecast": 1067,
        "farmer": 1068,
        "amusement": 1069,
        "customers": 1070,
        "lay": 1071,
        "sofa": 1072,
        "presentations": 1073,
        "yard": 1074,
        "order": 1075,
        "researchers": 1076,
        "finding": 1077,
        "afternoon": 1078,
        "area": 1079,
        "borrowed": 1080,
        "committee": 1081,
        "action": 1082,
        "cancelled": 1083,
        "film": 1084,
        "festival": 1085,
        "documents": 1086,
        "diverse": 1087,
        "hall": 1088,
        "tight": 1089,
        "engineers": 1090,
        "monument": 1091,
        "neighborhood": 1092,
        "short": 1093,
        "common": 1094,
        "theme": 1095,
        "comfortable": 1096,
        "special": 1097,
        "care": 1098,
        "tools": 1099,
        "garage": 1100,
        "lectures": 1101,
        "developed": 1102,
        "treatment": 1103,
        "assortment": 1104,
        "tank": 1105,
        "waterfall": 1106,
        "eager": 1107,
        "selection": 1108,
        "impact": 1109,
        "cast": 1110,
        "earrings": 1111,
        "something": 1112,
        "choir": 1113,
        "warm": 1114,
        "animals": 1115,
        "zoo": 1116,
        "visitors": 1117,
        "courses": 1118,
        "athletes": 1119,
        "languages": 1120,
        "essays": 1121,
        "daughter": 1122,
        "traffic": 1123,
        "behavior": 1124,
        "fan": 1125,
        "chess": 1126,
        "fiction": 1127,
        "menu": 1128,
        "advice": 1129,
        "discovered": 1130,
        "concept": 1131,
        "clouds": 1132,
        "landscape": 1133,
        "oil": 1134,
        "child": 1135,
        "copies": 1136,
        "yoga": 1137,
        "featuring": 1138,
        "civilizations": 1139,
        "station": 1140,
        "displaying": 1141,
        "sunlight": 1142,
        "hospital": 1143,
        "implementing": 1144,
        "exploring": 1145,
        "guided": 1146,
        "cheering": 1147,
        "enjoying": 1148,
        "boarding": 1149,
        "anniversary": 1150,
        "ride": 1151,
        "adding": 1152,
        "divided": 1153,
        "four": 1154,
        "near": 1155,
        "lake": 1156,
        "standing": 1157,
        "arrives": 1158,
        "corner": 1159,
        "climbed": 1160,
        "behind": 1161,
        "front": 1162,
        "airport": 1163,
        "pay": 1164,
        "shoulder": 1165,
        "hanging": 1166,
        "playground": 1167,
        "mystery": 1168,
        "novels": 1169,
        "died": 1170,
        "blood": 1171,
        "pressure": 1172,
        "forgets": 1173,
        "appointment": 1174,
        "cups": 1175,
        "floor": 1176,
        "backyard": 1177,
        "picked": 1178,
        "nearest": 1179,
        "upset": 1180,
        "forget": 1181,
        "dirty": 1182,
        "semester": 1183,
        "ocean": 1184,
        "flour": 1185,
        "driving": 1186,
        "crying": 1187,
        "serves": 1188,
        "songs": 1189,
        "accident": 1190,
        "roads": 1191,
        "wagging": 1192,
        "revenue": 1193,
        "camera": 1194,
        "call": 1195,
        "elephant": 1196,
        "dont": 1197,
        "cute": 1198,
        "london": 1199,
        "forgot": 1200,
        "vanilla": 1201,
        "lottery": 1202,
        "we'll": 1203,
        "first": 1204,
        "laundry": 1205,
        "calling": 1206,
        "terrible": 1207,
        "singer": 1208,
        "lights": 1209,
        "fantastic": 1210,
        "opened": 1211,
        "drinks": 1212,
        "impressed": 1213,
        "called": 1214,
        "exchange": 1215,
        "author's": 1216,
        "virus": 1217,
        "adapt": 1218,
        "left": 1219,
        "multiple": 1220,
        "allergic": 1221,
        "cats": 1222,
        "lose": 1223,
        "approaching": 1224,
        "voice": 1225,
        "passed": 1226,
        "name": 1227,
        "college": 1228,
        "sad": 1229,
        "baking": 1230,
        "porch": 1231,
        "soothing": 1232,
        "relaxing": 1233,
        "intense": 1234,
        "fans": 1235,
        "sky": 1236,
        "nobody": 1237,
        "rsvp": 1238,
        "furious": 1239,
        "situation": 1240,
        "details": 1241,
        "information": 1242,
        "comparing": 1243,
        "burning": 1244,
        "candle": 1245,
        "smoke": 1246,
        "bridge": 1247,
        "let": 1248,
        "count": 1249,
        "chickens": 1250,
        "hatch": 1251,
        "thing": 1252,
        "enemies": 1253,
        "bold": 1254,
        "far": 1255,
        "heart": 1256,
        "pound": 1257,
        "cure": 1258,
        "penny": 1259,
        "saved": 1260,
        "45": 1261,
        "driven": 1262,
        "technician": 1263,
        "prescribed": 1264,
        "jane": 1265,
        "submitted": 1266,
        "client": 1267,
        "overtime": 1268,
        "directed": 1269,
        "signed": 1270,
        "reviewing": 1271,
        "wrapped": 1272,
        "photos": 1273,
        "tickets": 1274,
        "politician": 1275,
        "bicycle": 1276,
        "satisfied": 1277,
        "own": 1278,
        "supervisor": 1279,
        "once": 1280,
        "findings": 1281,
        "upcoming": 1282,
        "attended": 1283,
        "media": 1284,
        "handed": 1285,
        "sunny": 1286,
        "lawyer": 1287,
        "entertaining": 1288,
        "provoking": 1289,
        "maintained": 1290,
        "assignment": 1291,
        "coat": 1292,
        "simple": 1293,
        "noisy": 1294,
        "valuable": 1295,
        "shy": 1296,
        "dry": 1297,
        "dent": 1298,
        "covered": 1299,
        "controversial": 1300,
        "soft": 1301,
        "traveler": 1302,
        "paper": 1303,
        "surprise": 1304,
        "director": 1305,
        "twist": 1306,
        "eyes": 1307,
        "awards": 1308,
        "ceremony": 1309,
        "local": 1310,
        "updates": 1311,
        "approach": 1312,
        "trends": 1313,
        "tastier": 1314,
        "mine": 1315,
        "colder": 1316,
        "hers": 1317,
        "hardest": 1318,
        "affordable": 1319,
        "option": 1320,
        "spacious": 1321,
        "spain": 1322,
        "quit": 1323,
        "cozy": 1324,
        "innovations": 1325,
        "essay": 1326,
        "natural": 1327,
        "texture": 1328,
        "expects": 1329,
        "punctual": 1330,
        "discusses": 1331,
        "politics": 1332,
        "insights": 1333,
        "weights": 1334,
        "cardio": 1335,
        "encourages": 1336,
        "showcases": 1337,
        "examines": 1338,
        "accommodation": 1339,
        "helpful": 1340,
        "collaboration": 1341,
        "big": 1342,
        "seminar": 1343,
        "management": 1344,
        "develop": 1345,
        "strength": 1346,
        "fashion": 1347,
        "tips": 1348,
        "web": 1349,
        "cars": 1350,
        "smartphones": 1351,
        "native": 1352,
        "album": 1353,
        "participants": 1354,
        "honest": 1355,
        "professionals": 1356,
        "essential": 1357,
        "critically": 1358,
        "reason": 1359,
        "spoke": 1360,
        "woman": 1361,
        "already": 1362,
        "complex": 1363,
        "overview": 1364,
        "conclusion": 1365,
        "peak": 1366,
        "comprehensive": 1367,
        "crime": 1368,
        "empty": 1369,
        "original": 1370,
        "provide": 1371,
        "process": 1372,
        "gotta": 1373,
        "experiment's": 1374,
        "refrain": 1375,
        "red": 1376,
        "sales": 1377,
        "others": 1378,
        "politician's": 1379,
        "kinda": 1380,
        "environment": 1381,
        "interface": 1382,
        "opportunity": 1383,
        "construction": 1384,
        "hurt": 1385,
        "ears": 1386,
        "curly": 1387,
        "understand": 1388,
        "compromise": 1389,
        "picnic": 1390,
        "argue": 1391,
        "spanish": 1392,
        "smarter": 1393,
        "california": 1394,
        "wore": 1395,
        "version": 1396,
        "competitor's": 1397,
        "higher": 1398,
        "speaking": 1399,
        "city's": 1400,
        "rapidly": 1401,
        "move": 1402,
        "accept": 1403,
        "passwords": 1404,
        "flight": 1405,
        "easy": 1406,
        "reach": 1407,
        "boss": 1408,
        "face": 1409,
        "dozen": 1410,
        "worlds": 1411,
        "advocate": 1412,
        "low": 1413,
        "app": 1414,
        "considering": 1415,
        "states": 1416,
        "child's": 1417,
        "check": 1418,
        "their's": 1419,
        "worried": 1420,
        "manage": 1421,
        "bike": 1422,
        "atmosphere": 1423,
        "reputation": 1424,
        "style": 1425,
        "breathtaking": 1426,
        "support": 1427,
        "proofread": 1428,
        "explore": 1429,
        "express": 1430,
        "waste": 1431,
        "analyze": 1432,
        "reduce": 1433,
        "opportunities": 1434,
        "promote": 1435,
        "meals": 1436,
        "allows": 1437,
        "users": 1438,
        "reducing": 1439,
        "improving": 1440,
        "career": 1441,
        "thinks": 1442,
        "leaves": 1443,
        "everyday": 1444,
        "barks": 1445,
        "sings": 1446,
        "cry": 1447,
        "wins": 1448,
        "moving": 1449,
        "brings": 1450,
        "delay": 1451,
        "cancel": 1452,
        "runs": 1453,
        "practices": 1454,
        "designs": 1455,
        "doctors": 1456,
        "bunch": 1457,
        "collaborate": 1458,
        "keeps": 1459,
        "revolves": 1460,
        "member": 1461,
        "brought": 1462,
        "principal": 1463,
        "explaining": 1464,
        "practicing": 1465,
        "collecting": 1466,
        "scored": 1467,
        "repairing": 1468,
        "threw": 1469,
        "washington": 1470,
        "among": 1471,
        "purse": 1472,
        "doctor's": 1473,
        "stopped": 1474,
        "talent": 1475,
        "childrens": 1476,
        "layed": 1477,
        "cool": 1478,
        "buying": 1479,
        "yet": 1480,
        "helps": 1481,
        "closes": 1482,
        "opens": 1483,
        "belongs": 1484,
        "axe": 1485,
        "young": 1486,
        "75": 1487,
        "charging": 1488,
        "further": 1489,
        "affects": 1490,
        "engaged": 1491,
        "clear": 1492,
        "continuously": 1493,
        "holiday": 1494,
        "speed": 1495,
        "bush": 1496,
        "silver": 1497,
        "stone": 1498,
        "bite": 1499,
        "spilled": 1500,
        "sight": 1501,
        "cooks": 1502,
        "squeaky": 1503,
        "gets": 1504,
        "grease": 1505,
        "fair": 1506,
        "power": 1507,
        "painted": 1508,
        "accepted": 1509,
        "arranged": 1510,
        "published": 1511,
        "assistant": 1512,
        "moved": 1513,
        "relax": 1514,
        "demanding": 1515,
        "environmental": 1516,
        "outstanding": 1517,
        "solving": 1518,
        "actress": 1519,
        "taught": 1520,
        "level": 1521,
        "solved": 1522,
        "organizing": 1523,
        "motivated": 1524,
        "participate": 1525,
        "presents": 1526,
        "smartphone": 1527,
        "uses": 1528,
        "increase": 1529,
        "thinking": 1530,
        "safety": 1531,
        "gradually": 1532,
        "coding": 1533,
        "sustainable": 1534,
        "possible": 1535,
        "why": 1536,
        "unexpected": 1537,
        "brief": 1538,
        "cannot": 1539,
        "kinds": 1540,
        "exceptional": 1541,
        "pretty": 1542,
        "intern": 1543,
        "act": 1544,
        "scientific": 1545,
        "encouraged": 1546,
        "miles": 1547,
        "stayed": 1548,
        "smoking": 1549,
        "apologize": 1550,
        "bigger": 1551,
        "funnier": 1552,
        "smaller": 1553,
        "elegant": 1554,
        "bloomed": 1555,
        "below": 1556,
        "spend": 1557,
        "hasn't": 1558,
        "bit": 1559,
        "confident": 1560,
        "hitting": 1561,
        "drawing": 1562,
        "doc": 1563,
        "nxt": 1564,
        "update": 1565,
        "stay": 1566,
        "certified": 1567,
        "we're": 1568,
        "sold": 1569,
        "award": 1570,
        "travels": 1571,
        "communicate": 1572,
        "invest": 1573,
        "cause": 1574,
        "carbon": 1575,
        "being": 1576,
        "enhancing": 1577,
        "drugs": 1578,
        "police": 1579,
        "primary": 1580,
        "responsibility": 1581,
        "artificial": 1582,
        "intelligence": 1583,
        "creative": 1584,
        "managing": 1585,
        "featured": 1586,
        "light": 1587,
        "efficiency": 1588,
        "effective": 1589,
        "stretching": 1590,
        "financial": 1591,
        "organization": 1592,
        "jobs": 1593,
        "strategies": 1594,
        "investment": 1595,
        "improvements": 1596,
        "upon": 1597,
        "creating": 1598,
        "providing": 1599,
        "east": 1600,
        "daily": 1601,
        "vacations": 1602,
        "clearly": 1603,
        "bloom": 1604,
        "studies": 1605,
        "ten": 1606,
        "swims": 1607,
        "medal": 1608,
        "sandcastle": 1609,
        "draw": 1610,
        "portrait": 1611,
        "seeds": 1612,
        "pilot": 1613,
        "delivery": 1614,
        "planner": 1615,
        "fixing": 1616,
        "prepare": 1617,
        "deliver": 1618,
        "teenager": 1619,
        "fridays": 1620,
        "hole": 1621,
        "waitress": 1622,
        "tuesday": 1623,
        "solution": 1624,
        "pile": 1625,
        "stamps": 1626,
        "steadily": 1627,
        "updated": 1628,
        "revision": 1629,
        "clapping": 1630,
        "enthusiastically": 1631,
        "constantly": 1632,
        "evolving": 1633,
        "diligently": 1634,
        "bakeries": 1635,
        "pastries": 1636,
        "sink": 1637,
        "lineup": 1638,
        "grown": 1639,
        "significantly": 1640,
        "shelves": 1641,
        "faculty": 1642,
        "leading": 1643,
        "incident": 1644,
        "laws": 1645,
        "physics": 1646,
        "governs": 1647,
        "universe": 1648,
        "protestors": 1649,
        "chanting": 1650,
        "flock": 1651,
        "counter": 1652,
        "overwhelming": 1653,
        "stack": 1654,
        "sorted": 1655,
        "families": 1656,
        "potluck": 1657,
        "stories": 1658,
        "bundle": 1659,
        "letters": 1660,
        "tied": 1661,
        "ribbon": 1662,
        "jeans": 1663,
        "greenhouse": 1664,
        "immensely": 1665,
        "creates": 1666,
        "herd": 1667,
        "cows": 1668,
        "graze": 1669,
        "parade": 1670,
        "tirelessly": 1671,
        "candies": 1672,
        "horizon": 1673,
        "tests": 1674,
        "rules": 1675,
        "aviary": 1676,
        "styles": 1677,
        "grapes": 1678,
        "rot": 1679,
        "socks": 1680,
        "holes": 1681,
        "vast": 1682,
        "cluster": 1683,
        "constellation": 1684,
        "government's": 1685,
        "significant": 1686,
        "rehearsing": 1687,
        "deer": 1688,
        "grazes": 1689,
        "meadow": 1690,
        "misplaced": 1691,
        "cupboard": 1692,
        "antique": 1693,
        "dancers": 1694,
        "unison": 1695,
        "buffet": 1696,
        "spectators": 1697,
        "writers": 1698,
        "script": 1699,
        "toys": 1700,
        "singers": 1701,
        "enlightening": 1702,
        "gloves": 1703,
        "characters": 1704,
        "memorable": 1705,
        "share": 1706,
        "edited": 1707,
        "shaker": 1708,
        "finance": 1709,
        "industry": 1710,
        "sunshine": 1711,
        "television": 1712,
        "watercolor": 1713,
        "chemistry": 1714,
        "newspaper": 1715,
        "drinking": 1716,
        "psychology": 1717,
        "springtime": 1718,
        "language": 1719,
        "radio": 1720,
        "branch": 1721,
        "lifestyle": 1722,
        "investing": 1723,
        "renewable": 1724,
        "classical": 1725,
        "sand": 1726,
        "constructing": 1727,
        "signing": 1728,
        "telescope": 1729,
        "harvesting": 1730,
        "crops": 1731,
        "tropical": 1732,
        "island": 1733,
        "exhibit": 1734,
        "wildlife": 1735,
        "error": 1736,
        "predicts": 1737,
        "recovering": 1738,
        "surgery": 1739,
        "nuts": 1740,
        "tour": 1741,
        "session": 1742,
        "sports": 1743,
        "conducting": 1744,
        "gate": 1745,
        "landmarks": 1746,
        "pocket": 1747,
        "listens": 1748,
        "monday": 1749,
        "flew": 1750,
        "talk": 1751,
        "looked": 1752,
        "leaning": 1753,
        "sat": 1754,
        "football": 1755,
        "entrance": 1756,
        "stadium": 1757,
        "fence": 1758,
        "italian": 1759,
        "sundays": 1760,
        "surprised": 1761,
        "depart": 1762,
        "placed": 1763,
        "village": 1764,
        "arguing": 1765,
        "bench": 1766,
        "surrounded": 1767,
        "tunnel": 1768,
        "bills": 1769,
        "carrying": 1770,
        "center": 1771,
        "chair": 1772,
        "pineapple": 1773,
        "able": 1774,
        "laptops": 1775,
        "faucet": 1776,
        "resigned": 1777,
        "drained": 1778,
        "medication": 1779,
        "really": 1780,
        "moves": 1781,
        "herself": 1782,
        "sleeps": 1783,
        "fireplace": 1784,
        "cousins": 1785,
        "peas": 1786,
        "hide": 1787,
        "seek": 1788,
        "00pm": 1789,
        "changed": 1790,
        "rang": 1791,
        "expecting": 1792,
        "alot": 1793,
        "orange": 1794,
        "couch": 1795,
        "350": 1796,
        "ill": 1797,
        "girls": 1798,
        "washing": 1799,
        "biology": 1800,
        "mammals": 1801,
        "stuck": 1802,
        "control": 1803,
        "conditions": 1804,
        "tomatoes": 1805,
        "carrots": 1806,
        "towels": 1807,
        "older": 1808,
        "younger": 1809,
        "51": 1810,
        "53": 1811,
        "guessed": 1812,
        "54": 1813,
        "55": 1814,
        "dusty": 1815,
        "56": 1816,
        "57": 1817,
        "intersection": 1818,
        "58": 1819,
        "happily": 1820,
        "59": 1821,
        "truly": 1822,
        "60": 1823,
        "61": 1824,
        "historic": 1825,
        "parks": 1826,
        "62": 1827,
        "flower": 1828,
        "cup": 1829,
        "63": 1830,
        "ease": 1831,
        "65": 1832,
        "colorful": 1833,
        "66": 1834,
        "69": 1835,
        "annual": 1836,
        "70": 1837,
        "73": 1838,
        "nap": 1839,
        "74": 1840,
        "forest": 1841,
        "76": 1842,
        "77": 1843,
        "tracks": 1844,
        "78": 1845,
        "causing": 1846,
        "crash": 1847,
        "79": 1848,
        "sandbox": 1849,
        "80": 1850,
        "finger": 1851,
        "peeling": 1852,
        "82": 1853,
        "postponed": 1854,
        "83": 1855,
        "85": 1856,
        "largest": 1857,
        "86": 1858,
        "87": 1859,
        "89": 1860,
        "90": 1861,
        "92": 1862,
        "lasagna": 1863,
        "93": 1864,
        "bakery": 1865,
        "donuts": 1866,
        "bagels": 1867,
        "94": 1868,
        "afraid": 1869,
        "ladder": 1870,
        "95": 1871,
        "97": 1872,
        "98": 1873,
        "projector": 1874,
        "whiteboard": 1875,
        "99": 1876,
        "100": 1877,
        "10th": 1878,
        "isnt": 1879,
        "pasta": 1880,
        "burgers": 1881,
        "im": 1882,
        "wet": 1883,
        "wagged": 1884,
        "harry": 1885,
        "potter": 1886,
        "lord": 1887,
        "rings": 1888,
        "warrant": 1889,
        "investigation": 1890,
        "weather's": 1891,
        "tennis": 1892,
        "cheese": 1893,
        "subjects": 1894,
        "blew": 1895,
        "preheat": 1896,
        "350f": 1897,
        "mix": 1898,
        "purple": 1899,
        "id": 1900,
        "nonstop": 1901,
        "lock": 1902,
        "louvre": 1903,
        "eiffel": 1904,
        "tower": 1905,
        "excepted": 1906,
        "complimentary": 1907,
        "colleague": 1908,
        "teachers": 1909,
        "rate": 1910,
        "preface": 1911,
        "followed": 1912,
        "sneakers": 1913,
        "throat": 1914,
        "headache": 1915,
        "discrete": 1916,
        "suspect": 1917,
        "gratitude": 1918,
        "devastating": 1919,
        "complimented": 1920,
        "appearance": 1921,
        "dealings": 1922,
        "reluctant": 1923,
        "apology": 1924,
        "pet": 1925,
        "advertisement": 1926,
        "apply": 1927,
        "gas": 1928,
        "max": 1929,
        "knows": 1930,
        "luna": 1931,
        "promotion": 1932,
        "dvds": 1933,
        "favor": 1934,
        "roof": 1935,
        "sunglasses": 1936,
        "streets": 1937,
        "flooded": 1938,
        "someone": 1939,
        "wind": 1940,
        "swaying": 1941,
        "fascinating": 1942,
        "boiling": 1943,
        "sunbathing": 1944,
        "waiters": 1945,
        "everywhere": 1946,
        "captivating": 1947,
        "admiring": 1948,
        "hot": 1949,
        "asleep": 1950,
        "relieved": 1951,
        "notes": 1952,
        "arriving": 1953,
        "wanting": 1954,
        "accidentally": 1955,
        "unclear": 1956,
        "whispered": 1957,
        "advance": 1958,
        "angry": 1959,
        "worms": 1960,
        "cross": 1961,
        "biting": 1962,
        "rocket": 1963,
        "omelette": 1964,
        "breaking": 1965,
        "steam": 1966,
        "grass": 1967,
        "greener": 1968,
        "side": 1969,
        "cloud": 1970,
        "lining": 1971,
        "thin": 1972,
        "built": 1973,
        "feeds": 1974,
        "thousand": 1975,
        "safe": 1976,
        "lead": 1977,
        "proof": 1978,
        "pudding": 1979,
        "beholder": 1980,
        "romans": 1981,
        "counts": 1982,
        "tricks": 1983,
        "spoil": 1984,
        "broth": 1985,
        "closer": 1986,
        "heads": 1987,
        "pot": 1988,
        "boils": 1989,
        "fortune": 1990,
        "favors": 1991,
        "those": 1992,
        "chain": 1993,
        "weakest": 1994,
        "link": 1995,
        "fall": 1996,
        "honey": 1997,
        "vinegar": 1998,
        "ignorance": 1999,
        "bliss": 2000,
        "minds": 2001,
        "alike": 2002,
        "absence": 2003,
        "fonder": 2004,
        "ounce": 2005,
        "prevention": 2006,
        "earned": 2007,
        "thicker": 2008,
        "mouth": 2009,
        "steady": 2010,
        "laughter": 2011,
        "jack": 2012,
        "hell": 2013,
        "paved": 2014,
        "intentions": 2015,
        "supermarket": 2016,
        "smith": 2017,
        "illness": 2018,
        "proposal": 2019,
        "tom": 2020,
        "secretary": 2021,
        "kevin": 2022,
        "susan": 2023,
        "mary": 2024,
        "forwarded": 2025,
        "jim": 2026,
        "invitation": 2027,
        "lisa": 2028,
        "attend": 2029,
        "florist": 2030,
        "contract": 2031,
        "terms": 2032,
        "mark": 2033,
        "grandmother": 2034,
        "peter": 2035,
        "rally": 2036,
        "tim": 2037,
        "emily": 2038,
        "composed": 2039,
        "printed": 2040,
        "tended": 2041,
        "throughout": 2042,
        "movers": 2043,
        "baker": 2044,
        "pruned": 2045,
        "sculpture": 2046,
        "created": 2047,
        "clay": 2048,
        "metal": 2049,
        "council": 2050,
        "gathered": 2051,
        "anyone": 2052,
        "finishes": 2053,
        "ensure": 2054,
        "describe": 2055,
        "symptoms": 2056,
        "survival": 2057,
        "hold": 2058,
        "they've": 2059,
        "engineer": 2060,
        "explained": 2061,
        "technical": 2062,
        "aspects": 2063,
        "announced": 2064,
        "following": 2065,
        "popularity": 2066,
        "skyrocketed": 2067,
        "scenery": 2068,
        "cameras": 2069,
        "compliments": 2070,
        "designated": 2071,
        "spot": 2072,
        "newlyweds": 2073,
        "praise": 2074,
        "attendees": 2075,
        "experiences": 2076,
        "informed": 2077,
        "repairs": 2078,
        "proud": 2079,
        "achievements": 2080,
        "commands": 2081,
        "surroundings": 2082,
        "litter": 2083,
        "assigned": 2084,
        "availability": 2085,
        "windy": 2086,
        "lightweight": 2087,
        "messy": 2088,
        "lazy": 2089,
        "lively": 2090,
        "stylish": 2091,
        "reliable": 2092,
        "bitter": 2093,
        "rewarding": 2094,
        "inexperienced": 2095,
        "scenic": 2096,
        "effort": 2097,
        "adventurous": 2098,
        "incredibly": 2099,
        "sandwiches": 2100,
        "plates": 2101,
        "wheat": 2102,
        "teacher's": 2103,
        "cousin": 2104,
        "admired": 2105,
        "noticed": 2106,
        "laughing": 2107,
        "hallway": 2108,
        "rumor": 2109,
        "floating": 2110,
        "bankruptcy": 2111,
        "documentary": 2112,
        "narrated": 2113,
        "kittens": 2114,
        "mud": 2115,
        "jennifer's": 2116,
        "reviewers": 2117,
        "programmer": 2118,
        "loaded": 2119,
        "writer": 2120,
        "carried": 2121,
        "blanket": 2122,
        "awarded": 2123,
        "trophy": 2124,
        "excitement": 2125,
        "suitcase": 2126,
        "several": 2127,
        "recipient": 2128,
        "cherry": 2129,
        "renowned": 2130,
        "unusual": 2131,
        "pathway": 2132,
        "enthusiasm": 2133,
        "detective": 2134,
        "page": 2135,
        "political": 2136,
        "scandals": 2137,
        "uniforms": 2138,
        "courier": 2139,
        "reviewed": 2140,
        "critic": 2141,
        "scolded": 2142,
        "tears": 2143,
        "blocking": 2144,
        "cracked": 2145,
        "designer": 2146,
        "touch": 2147,
        "artists": 2148,
        "medieval": 2149,
        "lesson": 2150,
        "instructor": 2151,
        "precision": 2152,
        "analyst": 2153,
        "including": 2154,
        "barista": 2155,
        "tallest": 2156,
        "funniest": 2157,
        "stream": 2158,
        "wine": 2159,
        "longest": 2160,
        "compelling": 2161,
        "simpler": 2162,
        "laziest": 2163,
        "roller": 2164,
        "coaster": 2165,
        "scariest": 2166,
        "strongest": 2167,
        "happiest": 2168,
        "youngest": 2169,
        "farthest": 2170,
        "quickest": 2171,
        "oldest": 2172,
        "material": 2173,
        "durable": 2174,
        "puzzle": 2175,
        "skillful": 2176,
        "shortest": 2177,
        "route": 2178,
        "richest": 2179,
        "easiest": 2180,
        "highest": 2181,
        "mount": 2182,
        "everest": 2183,
        "deepest": 2184,
        "part": 2185,
        "mariana": 2186,
        "trench": 2187,
        "narrowest": 2188,
        "brightest": 2189,
        "star": 2190,
        "sirius": 2191,
        "superhero": 2192,
        "superman": 2193,
        "task": 2194,
        "hiking": 2195,
        "cheap": 2196,
        "dedicated": 2197,
        "focus": 2198,
        "vibrant": 2199,
        "shapes": 2200,
        "respectful": 2201,
        "meditation": 2202,
        "renovate": 2203,
        "walls": 2204,
        "carpet": 2205,
        "visualizations": 2206,
        "chopped": 2207,
        "onions": 2208,
        "minced": 2209,
        "garlic": 2210,
        "cultural": 2211,
        "lifting": 2212,
        "stretch": 2213,
        "accessories": 2214,
        "alterations": 2215,
        "sculptures": 2216,
        "peaceful": 2217,
        "jazz": 2218,
        "acoustic": 2219,
        "sets": 2220,
        "processor": 2221,
        "storytelling": 2222,
        "involve": 2223,
        "tours": 2224,
        "charcoal": 2225,
        "collages": 2226,
        "grammar": 2227,
        "vocabulary": 2228,
        "pronunciation": 2229,
        "website": 2230,
        "pieces": 2231,
        "videos": 2232,
        "values": 2233,
        "ethic": 2234,
        "included": 2235,
        "opening": 2236,
        "guest": 2237,
        "speakers": 2238,
        "energetic": 2239,
        "unforgettable": 2240,
        "productivity": 2241,
        "living": 2242,
        "setting": 2243,
        "proper": 2244,
        "technique": 2245,
        "interviews": 2246,
        "rooftop": 2247,
        "views": 2248,
        "portfolio": 2249,
        "agenda": 2250,
        "introductions": 2251,
        "electric": 2252,
        "nowadays": 2253,
        "authors": 2254,
        "visa": 2255,
        "requirements": 2256,
        "region": 2257,
        "theory": 2258,
        "buildings": 2259,
        "skyscrapers": 2260,
        "machines": 2261,
        "costumes": 2262,
        "developers": 2263,
        "linux": 2264,
        "migratory": 2265,
        "layovers": 2266,
        "hotels": 2267,
        "fully": 2268,
        "booked": 2269,
        "accredited": 2270,
        "past": 2271,
        "decade": 2272,
        "classics": 2273,
        "catchy": 2274,
        "within": 2275,
        "limit": 2276,
        "vegetarian": 2277,
        "endangered": 2278,
        "politicians": 2279,
        "country": 2280,
        "attentive": 2281,
        "wood": 2282,
        "workout": 2283,
        "materials": 2284,
        "houses": 2285,
        "items": 2286,
        "camping": 2287,
        "toolbox": 2288,
        "rusty": 2289,
        "perennials": 2290,
        "vending": 2291,
        "unhealthy": 2292,
        "quiz": 2293,
        "phones": 2294,
        "models": 2295,
        "streaming": 2296,
        "platform": 2297,
        "acclaimed": 2298,
        "repeat": 2299,
        "again": 2300,
        "exaggerates": 2301,
        "outcome": 2302,
        "dinosaurs": 2303,
        "existed": 2304,
        "ago": 2305,
        "combined": 2306,
        "achieve": 2307,
        "individual": 2308,
        "slices": 2309,
        "absolutely": 2310,
        "certain": 2311,
        "nurse": 2312,
        "kitten": 2313,
        "repeated": 2314,
        "enthusiastic": 2315,
        "analyzed": 2316,
        "examined": 2317,
        "mentioned": 2318,
        "return": 2319,
        "ways": 2320,
        "brown": 2321,
        "conclusive": 2322,
        "fact": 2323,
        "disputed": 2324,
        "devastated": 2325,
        "fruits": 2326,
        "criminal": 2327,
        "guilty": 2328,
        "suddenly": 2329,
        "competent": 2330,
        "kindly": 2331,
        "burger": 2332,
        "fries": 2333,
        "coke": 2334,
        "consists": 2335,
        "requested": 2336,
        "asap": 2337,
        "inform": 2338,
        "unforeseen": 2339,
        "circumstances": 2340,
        "gimme": 2341,
        "shoulda": 2342,
        "handling": 2343,
        "equipment": 2344,
        "demonstrated": 2345,
        "slang": 2346,
        "dude": 2347,
        "property": 2348,
        "venue": 2349,
        "delish": 2350,
        "purpose": 2351,
        "sophisticated": 2352,
        "lemme": 2353,
        "assistance": 2354,
        "learner": 2355,
        "wild": 2356,
        "agreed": 2357,
        "proposed": 2358,
        "objective": 2359,
        "determine": 2360,
        "urged": 2361,
        "proactive": 2362,
        "mixture": 2363,
        "tradition": 2364,
        "modernity": 2365,
        "super": 2366,
        "bugs": 2367,
        "y'all": 2368,
        "promises": 2369,
        "workin'": 2370,
        "eco": 2371,
        "depth": 2372,
        "employee's": 2373,
        "complaint": 2374,
        "unfair": 2375,
        "toxic": 2376,
        "handbook": 2377,
        "contains": 2378,
        "procedures": 2379,
        "intuitive": 2380,
        "disease": 2381,
        "artwork": 2382,
        "simply": 2383,
        "responsible": 2384,
        "ambiance": 2385,
        "chill": 2386,
        "investigate": 2387,
        "term": 2388,
        "deprivation": 2389,
        "mental": 2390,
        "mission": 2391,
        "positive": 2392,
        "society": 2393,
        "contractor": 2394,
        "explores": 2395,
        "themes": 2396,
        "perspective": 2397,
        "relationships": 2398,
        "intriguing": 2399,
        "grocery": 2400,
        "picking": 2401,
        "forgotten": 2402,
        "leader": 2403,
        "hid": 2404,
        "sign": 2405,
        "drove": 2406,
        "candy": 2407,
        "shines": 2408,
        "arm": 2409,
        "chases": 2410,
        "rains": 2411,
        "indoors": 2412,
        "sick": 2413,
        "president": 2414,
        "practiced": 2415,
        "another": 2416,
        "paid": 2417,
        "recommend": 2418,
        "stubborn": 2419,
        "reached": 2420,
        "rested": 2421,
        "wouldn't": 2422,
        "snowball": 2423,
        "fight": 2424,
        "healthier": 2425,
        "helped": 2426,
        "taller": 2427,
        "becoming": 2428,
        "sam": 2429,
        "countryside": 2430,
        "canada": 2431,
        "newest": 2432,
        "deeper": 2433,
        "happier": 2434,
        "lighter": 2435,
        "safer": 2436,
        "motorcycle": 2437,
        "anticipated": 2438,
        "journey": 2439,
        "sweeter": 2440,
        "lazier": 2441,
        "thinner": 2442,
        "cleaner": 2443,
        "singing": 2444,
        "cheaper": 2445,
        "soup": 2446,
        "saltier": 2447,
        "salad": 2448,
        "jokes": 2449,
        "hill": 2450,
        "pie": 2451,
        "o'clock": 2452,
        "ringing": 2453,
        "answering": 2454,
        "brightly": 2455,
        "rare": 2456,
        "practice": 2457,
        "population": 2458,
        "starting": 2459,
        "five": 2460,
        "driveway": 2461,
        "horror": 2462,
        "freezing": 2463,
        "heavily": 2464,
        "stopping": 2465,
        "unprepared": 2466,
        "worry": 2467,
        "italy": 2468,
        "pets": 2469,
        "single": 2470,
        "wear": 2471,
        "jewelry": 2472,
        "emails": 2473,
        "excuses": 2474,
        "evidence": 2475,
        "violence": 2476,
        "fridge": 2477,
        "alcohol": 2478,
        "apologies": 2479,
        "explanation": 2480,
        "solutions": 2481,
        "pack": 2482,
        "extra": 2483,
        "fancy": 2484,
        "newspapers": 2485,
        "remember": 2486,
        "foreign": 2487,
        "packages": 2488,
        "lift": 2489,
        "available": 2490,
        "handle": 2491,
        "flavors": 2492,
        "packed": 2493,
        "expect": 2494,
        "loved": 2495,
        "minute": 2496,
        "peanuts": 2497,
        "unpopular": 2498,
        "likely": 2499,
        "maintenance": 2500,
        "online": 2501,
        "pick": 2502,
        "cores": 2503,
        "dunno": 2504,
        "python": 2505,
        "cellphone's": 2506,
        "who's": 2507,
        "impress": 2508,
        "try": 2509,
        "sushi": 2510,
        "app's": 2511,
        "clunky": 2512,
        "client's": 2513,
        "server": 2514,
        "attack": 2515,
        "expo": 2516,
        "later": 2517,
        "plumber": 2518,
        "busted": 2519,
        "pipe": 2520,
        "rollercoaster": 2521,
        "stand": 2522,
        "speeding": 2523,
        "hacker": 2524,
        "brainstorm": 2525,
        "checked": 2526,
        "total": 2527,
        "tech": 2528,
        "rope": 2529,
        "guess": 2530,
        "tip": 2531,
        "iceberg": 2532,
        "reinvent": 2533,
        "putting": 2534,
        "father's": 2535,
        "blessing": 2536,
        "disguise": 2537,
        "needle": 2538,
        "haystack": 2539,
        "grind": 2540,
        "chip": 2541,
        "block": 2542,
        "dime": 2543,
        "knocks": 2544,
        "fry": 2545,
        "half": 2546,
        "calm": 2547,
        "cutting": 2548,
        "nose": 2549,
        "spite": 2550,
        "devil's": 2551,
        "nut": 2552,
        "crack": 2553,
        "jumping": 2554,
        "bandwagon": 2555,
        "molehill": 2556,
        "sharpest": 2557,
        "tool": 2558,
        "shed": 2559,
        "lines": 2560,
        "bull": 2561,
        "horns": 2562,
        "throwing": 2563,
        "bathwater": 2564,
        "turning": 2565,
        "blind": 2566,
        "wolf": 2567,
        "sheep's": 2568,
        "sleeve": 2569,
        "joined": 2570,
        "cmp": 2571,
        "pain": 2572,
        "pkg": 2573,
        "del'd": 2574,
        "getting": 2575,
        "file": 2576,
        "wk": 2577,
        "yr": 2578,
        "mall": 2579,
        "v": 2580,
        "accurate": 2581,
        "non": 2582,
        "profit": 2583,
        "cpu": 2584,
        "he'll": 2585,
        "5g": 2586,
        "eff": 2587,
        "rated": 2588,
        "rpt": 2589,
        "slowed": 2590,
        "focusing": 2591,
        "declared": 2592,
        "initiative": 2593,
        "scan": 2594,
        "revealed": 2595,
        "abnormalities": 2596,
        "addressed": 2597,
        "display": 2598,
        "beef": 2599,
        "1st": 2600,
        "audited": 2601,
        "locked": 2602,
        "key": 2603,
        "patients": 2604,
        "coming": 2605,
        "decide": 2606,
        "missing": 2607,
        "parking": 2608,
        "nearby": 2609,
        "fading": 2610,
        "washes": 2611,
        "paw": 2612,
        "climbing": 2613,
        "ending": 2614,
        "location": 2615,
        "tom's": 2616,
        "tires": 2617,
        "dim": 2618,
        "cake's": 2619,
        "motivation": 2620,
        "loss": 2621,
        "computer's": 2622,
        "value": 2623,
        "decreased": 2624,
        "school's": 2625,
        "improved": 2626,
        "ranking": 2627,
        "robot's": 2628,
        "advanced": 2629,
        "mountain's": 2630,
        "dog's": 2631,
        "fur": 2632,
        "groomed": 2633,
        "bug": 2634,
        "store's": 2635,
        "popular": 2636,
        "discounts": 2637,
        "denying": 2638,
        "round": 2639,
        "bird's": 2640,
        "melody": 2641,
        "recipe's": 2642,
        "ingredient": 2643,
        "cinnamon": 2644,
        "flavor": 2645,
        "project's": 2646,
        "usually": 2647,
        "closing": 2648,
        "ended": 2649,
        "stunning": 2650,
        "seafood": 2651,
        "mindfulness": 2652,
        "site": 2653,
        "talked": 2654,
        "exhibits": 2655,
        "artifacts": 2656,
        "grew": 2657,
        "benefits": 2658,
        "versatility": 2659,
        "cafe": 2660,
        "hometown": 2661,
        "ireland": 2662,
        "subscribed": 2663,
        "ruined": 2664,
        "attends": 2665,
        "campus": 2666,
        "apartment": 2667,
        "junk": 2668,
        "anymore": 2669,
        "revise": 2670,
        "hope": 2671,
        "safely": 2672,
        "chemicals": 2673,
        "airtight": 2674,
        "containers": 2675,
        "aspires": 2676,
        "architect": 2677,
        "planned": 2678,
        "accurately": 2679,
        "record": 2680,
        "gracefully": 2681,
        "stage": 2682,
        "levels": 2683,
        "actively": 2684,
        "successfully": 2685,
        "steak": 2686,
        "promptly": 2687,
        "reports": 2688,
        "eventually": 2689,
        "privately": 2690,
        "systematically": 2691,
        "thoroughly": 2692,
        "hired": 2693,
        "leisurely": 2694,
        "subtly": 2695,
        "promised": 2696,
        "immediately": 2697,
        "eloquently": 2698,
        "thoughts": 2699,
        "permanently": 2700,
        "delete": 2701,
        "accounts": 2702,
        "slowly": 2703,
        "explain": 2704,
        "cautiously": 2705,
        "navigate": 2706,
        "icy": 2707,
        "effectively": 2708,
        "collectively": 2709,
        "dramatically": 2710,
        "grades": 2711,
        "strategically": 2712,
        "ventures": 2713,
        "persuasively": 2714,
        "point": 2715,
        "uniquely": 2716,
        "himself": 2717,
        "convey": 2718,
        "positively": 2719,
        "dispose": 2720,
        "recycling": 2721,
        "bins": 2722,
        "collaboratively": 2723,
        "enter": 2724,
        "artistically": 2725,
        "capture": 2726,
        "coach": 2727,
        "aggressively": 2728,
        "defense": 2729,
        "changes": 2730,
        "strongly": 2731,
        "objectively": 2732,
        "passionately": 2733,
        "securely": 2734,
        "password": 2735,
        "funding": 2736,
        "constant": 2737,
        "attributable": 2738,
        "brush": 2739,
        "teeth": 2740,
        "prevent": 2741,
        "cavities": 2742,
        "flood": 2743,
        "jam": 2744,
        "obsessed": 2745,
        "vintage": 2746,
        "facts": 2747,
        "appreciate": 2748,
        "footprint": 2749,
        "student's": 2750,
        "punished": 2751,
        "accused": 2752,
        "bribery": 2753,
        "admit": 2754,
        "boy's": 2755,
        "concerned": 2756,
        "frequent": 2757,
        "avoid": 2758,
        "children's": 2759,
        "careless": 2760,
        "character": 2761,
        "technologies": 2762,
        "chef's": 2763,
        "signature": 2764,
        "herbs": 2765,
        "officer's": 2766,
        "hostage's": 2767,
        "heat": 2768,
        "book's": 2769,
        "fined": 2770,
        "engineer's": 2771,
        "inconvenience": 2772,
        "may": 2773,
        "unity": 2774,
        "architect's": 2775,
        "vision": 2776,
        "led": 2777,
        "creation": 2778,
        "hobbies": 2779,
        "analytical": 2780,
        "detail": 2781,
        "cybersecurity": 2782,
        "french": 2783,
        "gourmet": 2784,
        "passionate": 2785,
        "teaching": 2786,
        "emotions": 2787,
        "edit": 2788,
        "images": 2789,
        "moist": 2790,
        "responsibilities": 2791,
        "budgeting": 2792,
        "rooms": 2793,
        "amenities": 2794,
        "regular": 2795,
        "stress": 2796,
        "suspenseful": 2797,
        "merchandise": 2798,
        "sustainability": 2799,
        "expand": 2800,
        "persistent": 2801,
        "willing": 2802,
        "risks": 2803,
        "tested": 2804,
        "humidity": 2805,
        "air": 2806,
        "transparency": 2807,
        "accountability": 2808,
        "foster": 2809,
        "confidence": 2810,
        "examples": 2811,
        "device": 2812,
        "designed": 2813,
        "mobile": 2814,
        "applications": 2815,
        "competitive": 2816,
        "analyzing": 2817,
        "identifying": 2818,
        "raise": 2819,
        "charity": 2820,
        "importance": 2821,
        "lifelong": 2822,
        "poverty": 2823,
        "healthcare": 2824,
        "track": 2825,
        "expenses": 2826,
        "budgets": 2827,
        "receive": 2828,
        "contemporary": 2829,
        "performances": 2830,
        "preparation": 2831,
        "gain": 2832,
        "pursue": 2833,
        "businesses": 2834,
        "stimulate": 2835,
        "economic": 2836,
        "challenges": 2837,
        "players": 2838,
        "puzzles": 2839,
        "defeat": 2840,
        "celebrates": 2841,
        "culture": 2842,
        "networking": 2843,
        "brands": 2844,
        "deforestation": 2845,
        "conservation": 2846,
        "highlights": 2847,
        "govern": 2848,
        "beneath": 2849,
        "degrees": 2850,
        "unknown": 2851,
        "discreet": 2852,
        "bored": 2853,
        "developing": 2854,
        "average": 2855,
        "feel": 2856,
        "anybody": 2857,
        "highly": 2858,
        "somewhat": 2859,
        "repair": 2860,
        "extremely": 2861,
        "officer": 2862,
        "consumer": 2863,
        "document": 2864,
        "processing": 2865,
        "unit": 2866,
        "internet": 2867,
        "acid": 2868,
        "search": 2869,
        "whose": 2870,
        "promoting": 2871,
        "saidthe": 2872,
        "rises": 2873,
        "rise": 2874,
        "watches": 2875,
        "chase": 2876,
        "gives": 2877,
        "grading": 2878,
        "scores": 2879,
        "say": 2880,
        "begins": 2881,
        "serve": 2882,
        "examine": 2883,
        "frost": 2884,
        "dig": 2885,
        "fit": 2886,
        "looks": 2887,
        "stretches": 2888,
        "meets": 2889,
        "form": 2890,
        "continues": 2891,
        "cheers": 2892,
        "nests": 2893,
        "attracts": 2894,
        "organizes": 2895,
        "laying": 2896,
        "inside": 2897,
        "against": 2898,
        "until": 2899,
        "sung": 2900,
        "climbs": 2901,
        "finds": 2902,
        "catched": 2903,
        "charged": 2904,
        "travelling": 2905,
        "putted": 2906,
        "hang": 2907,
        "setted": 2908,
        "peoples": 2909,
        "throwed": 2910,
        "00am": 2911,
        "homeworks": 2912,
        "triying": 2913,
        "performence": 2914,
        "prefered": 2915,
        "excersise": 2916,
        "innnovative": 2917,
        "cryed": 2918,
        "degress": 2919,
        "washinton": 2920,
        "umbrela": 2921,
        "childs": 2922,
        "colours": 2923,
        "yelow": 2924,
        "mashine": 2925,
        "studing": 2926,
        "assistent": 2927,
        "fill": 2928,
        "travells": 2929,
        "moneys": 2930,
        "offen": 2931,
        "suger": 2932,
        "vehicel": 2933,
        "wheather": 2934,
        "varity": 2935,
        "potatos": 2936,
        "recieved": 2937,
        "unkown": 2938,
        "explaning": 2939,
        "bedsheet": 2940,
        "beacuse": 2941,
        "resturant": 2942,
        "suspence": 2943,
        "groing": 2944,
        "drumbs": 2945,
        "beutiful": 2946,
        "furnitures": 2947,
        "favorit": 2948,
        "nervus": 2949,
        "especialy": 2950,
        "happend": 2951,
        "breath": 2952,
        "impatiantly": 2953,
        "buetiful": 2954,
        "huddle": 2955,
        "sprikles": 2956,
        "tournment": 2957,
        "increasd": 2958,
        "mornig": 2959,
        "batery": 2960,
        "noice": 2961,
        "adress": 2962,
        "rail": 2963,
        "breaks": 2964,
        "sandcastels": 2965,
        "cutted": 2966,
        "3pm": 2967,
        "arives": 2968,
        "mamal": 2969,
        "tyre": 2970,
        "birthay": 2971,
        "unconfortable": 2972,
        "delisious": 2973,
        "breads": 2974,
        "hights": 2975,
        "pluged": 2976,
        "beautful": 2977,
        "equiped": 2978,
        "adviced": 2979,
        "theyre": 2980,
        "shoutedstop": 2981,
        "extreem": 2982,
        "loose": 2983,
        "effected": 2984,
        "advise": 2985,
        "desert": 2986,
        "principle": 2987,
        "currant": 2988,
        "de": 2989,
        "fragmented": 2990,
        "pear": 2991,
        "suite": 2992,
        "storey": 2993,
        "soar": 2994,
        "weak": 2995,
        "trialed": 2996,
        "affect": 2997,
        "principles": 2998,
        "descent": 2999,
        "conscience": 3000,
        "complementary": 3001,
        "except": 3002,
        "confidant": 3003,
        "brand": 3004,
        "tasty": 3005,
        "ahead": 3006,
        "cash": 3007,
        "sugary": 3008,
        "boat": 3009,
        "cat's": 3010,
        "grain": 3011,
        "tango": 3012,
        "frying": 3013,
        "pan": 3014,
        "cookie": 3015,
        "crumbles": 3016,
        "piece": 3017,
        "rolling": 3018,
        "gathers": 3019,
        "moss": 3020,
        "cart": 3021,
        "pen": 3022,
        "mightier": 3023,
        "sword": 3024,
        "spoon": 3025,
        "glitters": 3026,
        "silk": 3027,
        "sow's": 3028,
        "ear": 3029,
        "devil": 3030,
        "all's": 3031,
        "war": 3032,
        "leopard": 3033,
        "spots": 3034,
        "knowledge": 3035,
        "happiness": 3036,
        "choose": 3037,
        "waits": 3038,
        "dull": 3039,
        "given": 3040,
        "taken": 3041,
        "earliest": 3042,
        "independently": 3043,
        "preserve": 3044,
        "replaced": 3045,
        "add": 3046,
        "spending": 3047,
        "engage": 3048,
        "recommendations": 3049,
        "ultimate": 3050,
        "period": 3051,
        "truthful": 3052,
        "female": 3053,
        "tiny": 3054,
        "exact": 3055,
        "previously": 3056,
        "chilly": 3057,
        "softly": 3058,
        "height": 3059,
        "concise": 3060,
        "heartbroken": 3061,
        "humorous": 3062,
        "convicted": 3063,
        "vacant": 3064,
        "copy": 3065,
        "abruptly": 3066,
        "understanding": 3067,
        "capable": 3068,
        "yo": 3069,
        "how's": 3070,
        "hangin'": 3071,
        "mixin'": 3072,
        "bakin'": 3073,
        "submits": 3074,
        "event's": 3075,
        "totes": 3076,
        "abbrevs": 3077,
        "stealin'": 3078,
        "awesome": 3079,
        "makin'": 3080,
        "what's": 3081,
        "main": 3082,
        "reckon": 3083,
        "dope": 3084,
        "keen": 3085,
        "helpin'": 3086,
        "lit": 3087,
        "legit": 3088,
        "step": 3089,
        "trainin'": 3090,
        "reducin'": 3091,
        "conservin'": 3092,
        "update's": 3093,
        "baloney": 3094,
        "amazeballs": 3095,
        "developin'": 3096,
        "improvin'": 3097,
        "pricey": 3098,
        "trust": 3099,
        "subpar": 3100,
        "info": 3101,
        "'bout": 3102,
        "breathtakin'": 3103,
        "organizin'": 3104,
        "managin'": 3105,
        "providin'": 3106,
        "fastly": 3107,
        "anyways": 3108,
        "needing": 3109,
        "invite": 3110,
        "exercised": 3111,
        "forgiven": 3112,
        "prettier": 3113,
        "stricter": 3114,
        "nowhere": 3115,
        "weren't": 3116,
        "none": 3117,
        "imma": 3118,
        "grub": 3119,
        "else": 3120,
        "cpu's": 3121,
        "ol'": 3122,
        "hire's": 3123,
        "whiz": 3124,
        "kid": 3125,
        "photog": 3126,
        "snaps": 3127,
        "oughta": 3128,
        "ux": 3129,
        "comp": 3130,
        "sec": 3131,
        "ddos": 3132,
        "hardass": 3133,
        "demo": 3134,
        "wanna": 3135,
        "grab": 3136,
        "done": 3137,
        "hella": 3138,
        "friggin'": 3139,
        "meh": 3140,
        "cop": 3141,
        "zero": 3142,
        "exploit": 3143,
        "mad": 3144,
        "head": 3145,
        "irons": 3146,
        "deets": 3147,
        "acting": 3148,
        "intern's": 3149,
        "getter": 3150,
        "crazy": 3151,
        "snoozefest": 3152,
        "guy": 3153,
        "glitchy": 3154,
        "knack": 3155,
        "drop": 3156,
        "fb": 3157,
        "ms": 3158,
        "bro": 3159,
        "usmc": 3160,
        "yday": 3161,
        "pls": 3162,
        "prof": 3163,
        "ucla": 3164,
        "cs": 3165,
        "dept": 3166,
        "200hp": 3167,
        "300lb": 3168,
        "ft": 3169,
        "tq": 3170,
        "gdpr": 3171,
        "ccpa": 3172,
        "hdmi": 3173,
        "usb": 3174,
        "bt": 3175,
        "cnct": 3176,
        "nsaids": 3177,
        "usps": 3178,
        "ups": 3179,
        "b2b": 3180,
        "b2c": 3181,
        "svs": 3182,
        "h2o": 3183,
        "lvl": 3184,
        "ai": 3185,
        "ml": 3186,
        "plz": 3187,
        "pdf": 3188,
        "moma": 3189,
        "fav": 3190,
        "sxsw": 3191,
        "atm": 3192,
        "svc": 3193,
        "gps": 3194,
        "idk": 3195,
        "govt": 3196,
        "reg's": 3197,
        "co2": 3198,
        "ems": 3199,
        "org": 3200,
        "501c3": 3201,
        "ssd": 3202,
        "gpu": 3203,
        "sys": 3204,
        "uk": 3205,
        "eu": 3206,
        "mth": 3207,
        "conf": 3208,
        "iot": 3209,
        "1tsp": 3210,
        "2tbsp": 3211,
        "35mpg": 3212,
        "hwy": 3213,
        "os": 3214,
        "uxui": 3215,
        "impr": 3216,
        "pub'd": 3217,
        "nyt": 3218,
        "gdp": 3219,
        "sci": 3220,
        "dna": 3221,
        "rna": 3222,
        "strc": 3223,
        "actr": 3224,
        "oscar": 3225,
        "saas": 3226,
        "qtr": 3227,
        "avg": 3228,
        "temp": 3229,
        "75f": 3230,
        "sum": 3231,
        "seo": 3232,
        "sem": 3233,
        "strat": 3234,
        "rd": 3235,
        "proj": 3236,
        "un": 3237,
        "sdgs": 3238,
        "wi": 3239,
        "fi": 3240,
        "cont'l": 3241,
        "bfast": 3242,
        "ct": 3243,
        "tkt": 3244,
        "htl": 3245,
        "stm't": 3246,
        "prblms": 3247,
        "arr": 3248,
        "co": 3249,
        "csr": 3250,
        "memb": 3251,
        "pta": 3252,
        "tmrw": 3253,
        "mri": 3254,
        "smrtph": 3255,
        "oled": 3256,
        "bldg": 3257,
        "leed": 3258,
        "1lb": 3259,
        "grd": 3260,
        "jan": 3261,
        "fin'l": 3262,
        "stmnts": 3263,
        "cpa": 3264,
        "which's": 3265,
        "her's": 3266,
        "professionally": 3267,
        "bore": 3268,
        "organism's": 3269,
        "annoy": 3270,
        "dedicate": 3271,
        "disappoint": 3272,
        "collect": 3273,
        "misrepresent": 3274,
        "corrupt": 3275,
        "embarass": 3276,
        "demand": 3277,
        "congratulate": 3278,
        "innovate": 3279,
        "decline": 3280,
        "disturb": 3281,
        "criticize": 3282,
        "disqualify": 3283,
        "roast": 3284,
        "wilt": 3285,
        "amaze": 3286,
        "pollute": 3287,
        "injure": 3288,
        "provided": 3289,
        "presenting": 3290,
        "inspire": 3291,
        "evoke": 3292,
        "sharing": 3293,
        "oversee": 3294,
        "offering": 3295,
        "selling": 3296,
        "monitor": 3297,
        "measure": 3298,
        "arrange": 3299,
        "enhance": 3300,
        "propose": 3301,
        "bark": 3302,
        "slept": 3303,
        "buys": 3304,
        "cries": 3305,
        "swam": 3306,
        "graded": 3307,
        "says": 3308,
        "begin": 3309,
        "planting": 3310,
        "fell": 3311,
        "frosted": 3312,
        "digging": 3313,
        "fits": 3314,
        "forms": 3315,
        "tells": 3316,
        "continue": 3317,
        "cheer": 3318,
        "collaborates": 3319,
        "nest": 3320,
        "attract": 3321,
        "trains": 3322,
        "shares": 3323,
        "amidst": 3324,
        "alongside": 3325,
        "sang": 3326,
        "neighbor's": 3327,
        "egg": 3328,
        "owner's": 3329,
        "hung": 3330,
        "tries": 3331,
        "preferred": 3332,
        "these": 3333,
        "yellow": 3334,
        "often": 3335,
        "vehicle": 3336,
        "potatoes": 3337,
        "sheets": 3338,
        "suspense": 3339,
        "drums": 3340,
        "nervous": 3341,
        "bookshelf": 3342,
        "impatiently": 3343,
        "hurdle": 3344,
        "sprinkles": 3345,
        "tournament": 3346,
        "railroad": 3347,
        "brakes": 3348,
        "sandcastles": 3349,
        "mammal": 3350,
        "tire": 3351,
        "uncomfortable": 3352,
        "heights": 3353,
        "plugged": 3354,
        "equipped": 3355,
        "healthily": 3356,
        "youre": 3357,
        "shouted": 3358,
        "extreme": 3359,
        "affected": 3360,
        "compliment": 3361,
        "current": 3362,
        "foreword": 3363,
        "defragmented": 3364,
        "suit": 3365,
        "sore": 3366,
        "adept": 3367,
        "effect": 3368,
        "principals": 3369,
        "decent": 3370,
        "conscious": 3371,
        "ones": 3372,
        "wrote": 3373,
        "independent": 3374,
        "resource": 3375,
        "preservation": 3376,
        "replace": 3377,
        "participation": 3378,
        "educational": 3379,
        "photo": 3380,
        "capabilities": 3381,
        "engagement": 3382,
        "increases": 3383,
        "recommendation": 3384,
        "gradual": 3385,
        "discussions": 3386,
        "hello": 3387,
        "mixing": 3388,
        "regret": 3389,
        "entirely": 3390,
        "abbreviations": 3391,
        "stealing": 3392,
        "legitimate": 3393,
        "conserving": 3394,
        "insincerity": 3395,
        "relaxed": 3396,
        "anyway": 3397,
        "girl's": 3398,
        "drew": 3399,
        "invited": 3400,
        "listened": 3401,
        "apologized": 3402,
        "forgive": 3403,
        "snowed": 3404,
        "learned": 3405,
        "shorter": 3406,
        "cooler": 3407,
        "anywhere": 3408,
        "consequences": 3409,
        "type": 3410,
        "beyond": 3411,
        "moment": 3412,
        "distributed": 3413,
        "denial": 3414,
        "demonstrate": 3415,
        "indifferent": 3416,
        "vulnerability": 3417,
        "currently": 3418,
        "involved": 3419,
        "classified": 3420,
        "intensely": 3421,
        "specialist": 3422,
        "malfunctioning": 3423,
        "facebook": 3424,
        "microsoft": 3425,
        "marine": 3426,
        "corps": 3427,
        "los": 3428,
        "angeles": 3429,
        "200": 3430,
        "horsepower": 3431,
        "300": 3432,
        "feet": 3433,
        "torque": 3434,
        "general": 3435,
        "protection": 3436,
        "regulation": 3437,
        "privacy": 3438,
        "compliance": 3439,
        "definition": 3440,
        "multimedia": 3441,
        "universal": 3442,
        "serial": 3443,
        "bluetooth": 3444,
        "connectivity": 3445,
        "nonsteroidal": 3446,
        "anti": 3447,
        "inflammatory": 3448,
        "postal": 3449,
        "parcel": 3450,
        "portable": 3451,
        "format": 3452,
        "word": 3453,
        "southwest": 3454,
        "automated": 3455,
        "teller": 3456,
        "global": 3457,
        "positioning": 3458,
        "dioxide": 3459,
        "emissions": 3460,
        "501": 3461,
        "c": 3462,
        "solid": 3463,
        "state": 3464,
        "central": 3465,
        "graphics": 3466,
        "kingdom": 3467,
        "european": 3468,
        "union": 3469,
        "teaspoon": 3470,
        "tablespoons": 3471,
        "per": 3472,
        "gallon": 3473,
        "highway": 3474,
        "operating": 3475,
        "experienceuser": 3476,
        "gross": 3477,
        "domestic": 3478,
        "deoxyribonucleic": 3479,
        "ribonucleic": 3480,
        "structures": 3481,
        "academy": 3482,
        "quarter": 3483,
        "fahrenheit": 3484,
        "optimization": 3485,
        "nations": 3486,
        "wireless": 3487,
        "continental": 3488,
        "computed": 3489,
        "tomography": 3490,
        "statement": 3491,
        "chief": 3492,
        "executive": 3493,
        "corporate": 3494,
        "parent": 3495,
        "association": 3496,
        "magnetic": 3497,
        "resonance": 3498,
        "imaging": 3499,
        "inch": 3500,
        "organic": 3501,
        "emitting": 3502,
        "diode": 3503,
        "ground": 3504,
        "january": 3505,
        "statements": 3506,
        "accountant": 3507,
        "whom": 3508,
        "organisms'": 3509,
        "adaptation": 3510,
        "annoyed": 3511,
        "dedication": 3512,
        "disappointed": 3513,
        "resulting": 3514,
        "misrepresenting": 3515,
        "chewing": 3516,
        "corruption": 3517,
        "embarrassed": 3518,
        "lies": 3519,
        "congratulated": 3520,
        "declining": 3521,
        "disturbing": 3522,
        "disqualified": 3523,
        "roasting": 3524,
        "amazed": 3525,
        "polluting": 3526,
        "designing": 3527,
        "injured": 3528,
        "present": 3529,
        "inspiring": 3530,
        "evokes": 3531,
        "overseeing": 3532,
        "reduction": 3533,
        "monitoring": 3534,
        "measurement": 3535,
        "proposes": 3536,
        "exactly": 3537,
        "explains": 3538,
        "concepts": 3539
    },
    "num_words": 25000,
    "max_length": 120
}